pdaztables/__init__.py
pdAzTables-0.0.6.dist-info/LICENSE
pdAzTables-0.0.6.dist-info/METADATA
pdAzTables-0.0.6.dist-info/WHEEL
pdAzTables-0.0.6.dist-info/top_level.txt
pdAzTables-0.0.6.dist-info/RECORD
