Metadata-Version: 2.1
Name: pdAzTables
Version: 0.0.6
Summary: Easy Azure table storage into Pandas dataframe
Home-page: https://github.com/Gorgoras/PandasAzureTables
Author: Martin Zurita
Author-email: martinzurita1@gmail.com
License: MIT
Download-URL: https://github.com/Gorgoras/PandasAzureTables/archive/v0.0.4.tar.gz
Keywords: Pandas,Azure,NoSQL,Data
Platform: UNKNOWN
Classifier: Programming Language :: Python :: 3
Classifier: License :: OSI Approved :: MIT License
Classifier: Operating System :: OS Independent
Requires-Dist: azure-cosmosdb-table
Requires-Dist: pandas
